Metadata-Version: 2.1
Name: odoo14-addon-sale_report_delivery_date
Version: 14.0.1.0.1.dev7
Summary: Display the delivery date on Sales Order analysis reports
Home-page: https://github.com/OCA/sale-reporting
Author: Camptocamp, Odoo Community Association (OCA)
Author-email: support@odoo-community.org
License: AGPL-3
Classifier: Programming Language :: Python
Classifier: Framework :: Odoo
Classifier: Framework :: Odoo :: 14.0
Classifier: License :: OSI Approved :: GNU Affero General Public License v3
Requires-Python: >=3.6
Requires-Dist: odoo<14.1dev,>=14.0a
